frogml/__init__.py
frogml/_proto/com/jfrog/ml/model/deployment/v1/auto_scaling_pb2.py
frogml/_proto/com/jfrog/ml/model/deployment/v1/auto_scaling_pb2.pyi
frogml/_proto/com/jfrog/ml/model/deployment/v1/auto_scaling_pb2_grpc.py
frogml/_proto/com/jfrog/ml/model/deployment/v1/deployment_pb2.py
frogml/_proto/com/jfrog/ml/model/deployment/v1/deployment_pb2.pyi
frogml/_proto/com/jfrog/ml/model/deployment/v1/deployment_pb2_grpc.py
frogml/_proto/com/jfrog/ml/model/deployment/v1/deployment_service_pb2.py
frogml/_proto/com/jfrog/ml/model/deployment/v1/deployment_service_pb2.pyi
frogml/_proto/com/jfrog/ml/model/deployment/v1/deployment_service_pb2_grpc.py
frogml/_proto/com/jfrog/ml/model/deployment/v1/environment_variables_configuration_pb2.py
frogml/_proto/com/jfrog/ml/model/deployment/v1/environment_variables_configuration_pb2.pyi
frogml/_proto/com/jfrog/ml/model/deployment/v1/environment_variables_configuration_pb2_grpc.py
frogml/_proto/com/jfrog/ml/model/deployment/v1/model_artifact_identifier_pb2.py
frogml/_proto/com/jfrog/ml/model/deployment/v1/model_artifact_identifier_pb2.pyi
frogml/_proto/com/jfrog/ml/model/deployment/v1/model_artifact_identifier_pb2_grpc.py
frogml/_proto/com/jfrog/ml/model/deployment/v1/model_deployment_brief_pb2.py
frogml/_proto/com/jfrog/ml/model/deployment/v1/model_deployment_brief_pb2.pyi
frogml/_proto/com/jfrog/ml/model/deployment/v1/model_deployment_brief_pb2_grpc.py
frogml/_proto/com/jfrog/ml/model/deployment/v1/model_deployment_filter_pb2.py
frogml/_proto/com/jfrog/ml/model/deployment/v1/model_deployment_filter_pb2.pyi
frogml/_proto/com/jfrog/ml/model/deployment/v1/model_deployment_filter_pb2_grpc.py
frogml/_proto/com/jfrog/ml/model/deployment/v1/probes_configuration_pb2.py
frogml/_proto/com/jfrog/ml/model/deployment/v1/probes_configuration_pb2.pyi
frogml/_proto/com/jfrog/ml/model/deployment/v1/probes_configuration_pb2_grpc.py
frogml/_proto/com/jfrog/ml/model/deployment/v1/realtime_deployment_pb2.py
frogml-1.2.46.dist-info/METADATA
frogml-1.2.46.dist-info/WHEEL
frogml-1.2.46.dist-info/RECORD
