Metadata-Version: 2.3
Name: frogml
Version: 1.2.46
Summary: frogml contains the necessary objects and communication tools for using the JFrog ml Platform
License: Apache-2.0
Keywords: mlops,ml,deployment,serving,model
Author: JFrog
Requires-Python: >=3.9,<3.14
Classifier: License :: OSI Approved :: Apache Software License
Classifier: Operating System :: OS Independent
Classifier: Programming Language :: Python :: 3
Classifier: Programming Language :: Python :: 3.9
Classifier: Programming Language :: Python :: 3.10
Classifier: Programming Language :: Python :: 3.11
Classifier: Programming Language :: Python :: 3.12
Classifier: Programming Language :: Python :: 3.13
Classifier: Programming Language :: Python :: Implementation :: CPython
Classifier: Topic :: Scientific/Engineering :: Artificial Intelligence
Provides-Extra: catboost
Provides-Extra: feature-store
Provides-Extra: onnx
Provides-Extra: scikit-learn
Provides-Extra: torch
Provides-Extra: transformers
Requires-Dist: PyYAML (>=6.0.2)
Requires-Dist: cachetools (>=5.2,<7)
Requires-Dist: catboost (>=1.2.8,<2.0.0) ; extra == "catboost"
Requires-Dist: chevron (==0.14.0)
Requires-Dist: cloudpickle (==2.2.1)
Requires-Dist: dacite (==1.9.2)
Requires-Dist: dependency-injector (>=4.0)
Requires-Dist: filelock
Requires-Dist: grpcio (>=1.71.2,<1.75)
Requires-Dist: joblib (>=1.3.2,<2.0.0)
Requires-Dist: libcst (>=1.8.2,<2.0.0)
Requires-Dist: marshmallow-dataclass (>=8.5.8,<9.0.0)
Requires-Dist: onnx (>=1.18.0,<2.0.0) ; extra == "onnx"
Requires-Dist: pandas (>=1.4.0) ; extra == "feature-store"
Requires-Dist: protobuf (>=4.25.8,<5) ; python_version < "3.12"
Requires-Dist: protobuf (>=6.33.1,<7) ; python_version >= "3.12"
Requires-Dist: pyarrow (>=20.0.0) ; extra == "feature-store"
Requires-Dist: pyathena (>=2.2.0,!=2.18.0) ; extra == "feature-store"
Requires-Dist: pydantic
Requires-Dist: pyjwt (>=2.10.1,<3)
Requires-Dist: pyspark (==3.5.7) ; (python_version < "3.12") and (extra == "feature-store")
Requires-Dist: pyspark (>=4.0.1,<5) ; (python_version >= "3.12") and (extra == "feature-store")
Requires-Dist: python-json-logger (>=2.0.2)
Requires-Dist: requests
Requires-Dist: retrying (==1.4.2)
Requires-Dist: scikit-learn (>=1.5,<2.0) ; extra == "scikit-learn"
Requires-Dist: strenum (>=0.4.15,<0.5.0)
Requires-Dist: torch (>=2.7.1,<3.0.0) ; extra == "torch"
Requires-Dist: tqdm
Requires-Dist: transformers (>=4.53.0,<5.0.0) ; extra == "transformers"
Requires-Dist: typeguard (>=2,<3)
Project-URL: Home page, https://www.jfrog.com/
